pythonpy/__init__.py
pythonpy/__main__.py
pythonpy/__version__.py
pythonpy/pycompleter.py
pythonpy/pyeval.py
pythonpy/completion/__init__.py
pythonpy/completion/pycompletion.sh
pythonpy_fork-0.5.5.data/scripts/find_pycompletion.sh
pythonpy_fork-0.5.5.dist-info/COPYING.md
pythonpy_fork-0.5.5.dist-info/LICENSE.txt
pythonpy_fork-0.5.5.dist-info/METADATA
pythonpy_fork-0.5.5.dist-info/WHEEL
pythonpy_fork-0.5.5.dist-info/entry_points.txt
pythonpy_fork-0.5.5.dist-info/top_level.txt
pythonpy_fork-0.5.5.dist-info/RECORD
