Metadata-Version: 2.1
Name: pythonpy-fork
Version: 0.5.5
Summary: python -c, with tab completion and shorthand; fish2k fork
Home-page: https://github.com/fish2000/pythonpy-fork
License: MIT
License-File: LICENSE.txt
License-File: COPYING.md
